gitfx/__init__.py
gitfx/__main__.py
gitfx/lang_version.py
gitfx/parse_funcs.py
gitfx/run_funcs.py
GitFx-0.0.8.dist-info/LICENSE
GitFx-0.0.8.dist-info/METADATA
GitFx-0.0.8.dist-info/WHEEL
GitFx-0.0.8.dist-info/top_level.txt
GitFx-0.0.8.dist-info/RECORD
