Metadata-Version: 2.1
Name: GitFx
Version: 0.0.8
Summary: Create a Serverless service in Git hosting
Home-page: https://github.com/gitx-io/GitFx
Author: B1nj0y
Author-email: idegorepl@gmail.com
Project-URL: Bug Tracker, https://github.com/gitx-io/GitFx/issues
Classifier: Programming Language :: Python :: 3
Classifier: License :: OSI Approved :: Apache Software License
Classifier: Operating System :: OS Independent
Requires-Python: >=3.6
License-File: LICENSE
